beeptest/__init__.py
beeptest/booptest.py
beep_boop_test-0.1.dist-info/LICENSE
beep_boop_test-0.1.dist-info/METADATA
beep_boop_test-0.1.dist-info/WHEEL
beep_boop_test-0.1.dist-info/top_level.txt
beep_boop_test-0.1.dist-info/RECORD
