Metadata-Version: 2.1
Name: beep-boop-test
Version: 0.1
Summary: Beep? Boop!
Home-page: https://github.com/EduardAlex/beepboop
Author: David Eduard
Author-email: edyalex.david@gmail.com
License: UNKNOWN
Platform: UNKNOWN
Classifier: Programming Language :: Python :: 3
Classifier: License :: Public Domain
Classifier: Operating System :: OS Independent
Requires-Python: >=3.6
